map_with_stats/__init__.py
map_with_stats/_version.py
map_with_stats/data.py
map_with_stats/map.py
map_with_stats/py.typed
map_with_stats/utils.py
map_with_stats-0.2.0.dist-info/LICENSE
map_with_stats-0.2.0.dist-info/METADATA
map_with_stats-0.2.0.dist-info/WHEEL
map_with_stats-0.2.0.dist-info/top_level.txt
map_with_stats-0.2.0.dist-info/RECORD
