Metadata-Version: 2.1
Name: map_with_stats
Version: 0.2.0
Summary: Interactive map with a choropleth displaying some statistics as color per hectare
Author: Mischa Lisovyi
License: MIT License
Project-URL: Homepage, https://github.com/mlisovyi/map_with_stats
Project-URL: Documentation, https://mlisovyi.github.io/map_with_stats/
Classifier: Programming Language :: Python :: 3
Classifier: Programming Language :: Python :: 3.7
Classifier: Programming Language :: Python :: 3.8
Classifier: Programming Language :: Python :: 3.9
Classifier: Programming Language :: Python :: 3.10
Classifier: Programming Language :: Python :: 3.11
Classifier: Programming Language :: Python :: 3.12
Classifier: License :: OSI Approved :: MIT License
Classifier: Operating System :: OS Independent
Classifier: Typing :: Typed
Requires-Python: >=3.7
License-File: LICENSE
Requires-Dist: folium <1.0,>=0.10
Requires-Dist: geopandas <1.0,>=0.10
